Workbook

Sheet Inventory
A1: Fill in one row per item. The yellow columns are for you; Profit, Days online and Status calculate themselves.
A3: Item | B3: Purchase date | C3: Purchase price | D3: Marketplace | E3: Date listed | F3: Sale date | G3: Sale price | H3: Shipping cost (paid by you) | I3: Platform fees | J3: Profit | K3: Days online | L3: Status
J4: =IF(G4="","",G4-C4-H4-I4) | K4: =IF(E4="","",IF(F4="",TODAY(),F4)-E4) | L4: =IF(F4<>"","Sold",IF(E4<>"","Online",IF(A4<>"","In stock","")))
J5: =IF(G5="","",G5-C5-H5-I5) | K5: =IF(E5="","",IF(F5="",TODAY(),F5)-E5) | L5: =IF(F5<>"","Sold",IF(E5<>"","Online",IF(A5<>"","In stock","")))
J6: =IF(G6="","",G6-C6-H6-I6) | K6: =IF(E6="","",IF(F6="",TODAY(),F6)-E6) | L6: =IF(F6<>"","Sold",IF(E6<>"","Online",IF(A6<>"","In stock","")))
J7: =IF(G7="","",G7-C7-H7-I7) | K7: =IF(E7="","",IF(F7="",TODAY(),F7)-E7) | L7: =IF(F7<>"","Sold",IF(E7<>"","Online",IF(A7<>"","In stock","")))
J8: =IF(G8="","",G8-C8-H8-I8) | K8: =IF(E8="","",IF(F8="",TODAY(),F8)-E8) | L8: =IF(F8<>"","Sold",IF(E8<>"","Online",IF(A8<>"","In stock","")))
J9: =IF(G9="","",G9-C9-H9-I9) | K9: =IF(E9="","",IF(F9="",TODAY(),F9)-E9) | L9: =IF(F9<>"","Sold",IF(E9<>"","Online",IF(A9<>"","In stock","")))
J10: =IF(G10="","",G10-C10-H10-I10) | K10: =IF(E10="","",IF(F10="",TODAY(),F10)-E10) | L10: =IF(F10<>"","Sold",IF(E10<>"","Online",IF(A10<>"","In stock","")))
J11: =IF(G11="","",G11-C11-H11-I11) | K11: =IF(E11="","",IF(F11="",TODAY(),F11)-E11) | L11: =IF(F11<>"","Sold",IF(E11<>"","Online",IF(A11<>"","In stock","")))
J12: =IF(G12="","",G12-C12-H12-I12) | K12: =IF(E12="","",IF(F12="",TODAY(),F12)-E12) | L12: =IF(F12<>"","Sold",IF(E12<>"","Online",IF(A12<>"","In stock","")))
J13: =IF(G13="","",G13-C13-H13-I13) | K13: =IF(E13="","",IF(F13="",TODAY(),F13)-E13) | L13: =IF(F13<>"","Sold",IF(E13<>"","Online",IF(A13<>"","In stock","")))
J14: =IF(G14="","",G14-C14-H14-I14) | K14: =IF(E14="","",IF(F14="",TODAY(),F14)-E14) | L14: =IF(F14<>"","Sold",IF(E14<>"","Online",IF(A14<>"","In stock","")))
J15: =IF(G15="","",G15-C15-H15-I15) | K15: =IF(E15="","",IF(F15="",TODAY(),F15)-E15) | L15: =IF(F15<>"","Sold",IF(E15<>"","Online",IF(A15<>"","In stock","")))
... J503: =IF(G503="","",G503-C503-H503-I503) | K503: =IF(E503="","",IF(F503="",TODAY(),F503)-E503) | L503: =IF(F503<>"","Sold",IF(E503<>"","Online",IF(A503<>"","In stock","")))

Sheet Yearly overview
A1: Year | B1: 2026
A3: Platform | B3: Sales | C3: Revenue | D3: Profit | E3: DAC7: gets reported?
A4: Marktplaats | B4: =COUNTIFS('Inventory'!$D$4:$D$503,A4,'Inventory'!$F$4:$F$503,">="&DATE($B$1,1,1),'Inventory'!$F$4:$F$503,"<="&DATE($B$1,12,31)) | C4: =SUMIFS('Inventory'!$G$4:$G$503,'Inventory'!$D$4:$D$503,A4,'Inventory'!$F$4:$F$503,">="&DATE($B$1,1,1),'Inventory'!$F$4:$F$503,"<="&DATE($B$1,12,31)) | D4: =SUMIFS('Inventory'!$J$4:$J$503,'Inventory'!$D$4:$D$503,A4,'Inventory'!$F$4:$F$503,">="&DATE($B$1,1,1),'Inventory'!$F$4:$F$503,"<="&DATE($B$1,12,31)) | E4: =IF(OR(B4>=30,C4>2000),"Yes: the platform reports your details to the tax authority","No")
A5: 2dehands | B5: =COUNTIFS('Inventory'!$D$4:$D$503,A5,'Inventory'!$F$4:$F$503,">="&DATE($B$1,1,1),'Inventory'!$F$4:$F$503,"<="&DATE($B$1,12,31)) | C5: =SUMIFS('Inventory'!$G$4:$G$503,'Inventory'!$D$4:$D$503,A5,'Inventory'!$F$4:$F$503,">="&DATE($B$1,1,1),'Inventory'!$F$4:$F$503,"<="&DATE($B$1,12,31)) | D5: =SUMIFS('Inventory'!$J$4:$J$503,'Inventory'!$D$4:$D$503,A5,'Inventory'!$F$4:$F$503,">="&DATE($B$1,1,1),'Inventory'!$F$4:$F$503,"<="&DATE($B$1,12,31)) | E5: =IF(OR(B5>=30,C5>2000),"Yes: the platform reports your details to the tax authority","No")
A6: Vinted | B6: =COUNTIFS('Inventory'!$D$4:$D$503,A6,'Inventory'!$F$4:$F$503,">="&DATE($B$1,1,1),'Inventory'!$F$4:$F$503,"<="&DATE($B$1,12,31)) | C6: =SUMIFS('Inventory'!$G$4:$G$503,'Inventory'!$D$4:$D$503,A6,'Inventory'!$F$4:$F$503,">="&DATE($B$1,1,1),'Inventory'!$F$4:$F$503,"<="&DATE($B$1,12,31)) | D6: =SUMIFS('Inventory'!$J$4:$J$503,'Inventory'!$D$4:$D$503,A6,'Inventory'!$F$4:$F$503,">="&DATE($B$1,1,1),'Inventory'!$F$4:$F$503,"<="&DATE($B$1,12,31)) | E6: =IF(OR(B6>=30,C6>2000),"Yes: the platform reports your details to the tax authority","No")
A7: eBay | B7: =COUNTIFS('Inventory'!$D$4:$D$503,A7,'Inventory'!$F$4:$F$503,">="&DATE($B$1,1,1),'Inventory'!$F$4:$F$503,"<="&DATE($B$1,12,31)) | C7: =SUMIFS('Inventory'!$G$4:$G$503,'Inventory'!$D$4:$D$503,A7,'Inventory'!$F$4:$F$503,">="&DATE($B$1,1,1),'Inventory'!$F$4:$F$503,"<="&DATE($B$1,12,31)) | D7: =SUMIFS('Inventory'!$J$4:$J$503,'Inventory'!$D$4:$D$503,A7,'Inventory'!$F$4:$F$503,">="&DATE($B$1,1,1),'Inventory'!$F$4:$F$503,"<="&DATE($B$1,12,31)) | E7: =IF(OR(B7>=30,C7>2000),"Yes: the platform reports your details to the tax authority","No")
A8: Shopify | B8: =COUNTIFS('Inventory'!$D$4:$D$503,A8,'Inventory'!$F$4:$F$503,">="&DATE($B$1,1,1),'Inventory'!$F$4:$F$503,"<="&DATE($B$1,12,31)) | C8: =SUMIFS('Inventory'!$G$4:$G$503,'Inventory'!$D$4:$D$503,A8,'Inventory'!$F$4:$F$503,">="&DATE($B$1,1,1),'Inventory'!$F$4:$F$503,"<="&DATE($B$1,12,31)) | D8: =SUMIFS('Inventory'!$J$4:$J$503,'Inventory'!$D$4:$D$503,A8,'Inventory'!$F$4:$F$503,">="&DATE($B$1,1,1),'Inventory'!$F$4:$F$503,"<="&DATE($B$1,12,31)) | E8: =IF(OR(B8>=30,C8>2000),"Yes: the platform reports your details to the tax authority","No")
A9: Other | B9: =COUNTIFS('Inventory'!$D$4:$D$503,A9,'Inventory'!$F$4:$F$503,">="&DATE($B$1,1,1),'Inventory'!$F$4:$F$503,"<="&DATE($B$1,12,31)) | C9: =SUMIFS('Inventory'!$G$4:$G$503,'Inventory'!$D$4:$D$503,A9,'Inventory'!$F$4:$F$503,">="&DATE($B$1,1,1),'Inventory'!$F$4:$F$503,"<="&DATE($B$1,12,31)) | D9: =SUMIFS('Inventory'!$J$4:$J$503,'Inventory'!$D$4:$D$503,A9,'Inventory'!$F$4:$F$503,">="&DATE($B$1,1,1),'Inventory'!$F$4:$F$503,"<="&DATE($B$1,12,31)) | E9: =IF(OR(B9>=30,C9>2000),"Yes: the platform reports your details to the tax authority","No")
A10: Total | B10: =SUM(B4:B9) | C10: =SUM(C4:C9) | D10: =SUM(D4:D9)
A12: DAC7 limit (Dutch Belastingdienst, per platform and calendar year): 30 sales or more, or revenue above 2,000 euro. Being reported is not the same as paying tax. This is not tax advice.
